{
  "last_run": "2026-03-11T18:25:27.971738Z",
  "status": "success",
  "sources": {
    "wikipedia": {
      "rows": 8279,
      "status": "ok"
    },
    "espn_games": {
      "rows": 1624,
      "status": "ok"
    },
    "news": {
      "rows": 790,
      "status": "ok"
    },
    "attendance": {
      "rows": 565,
      "status": "ok"
    },
    "tickets": {
      "rows": 0,
      "status": "ok"
    },
    "youtube": {
      "rows": 60,
      "status": "ok"
    },
    "betting": {
      "rows": 60,
      "status": "ok"
    }
  }
}